setup.py
s3vcp/__init__.py
s3vcp/s3vcp.py
s3vcp.egg-info/PKG-INFO
s3vcp.egg-info/SOURCES.txt
s3vcp.egg-info/dependency_links.txt
s3vcp.egg-info/entry_points.txt
s3vcp.egg-info/requires.txt
s3vcp.egg-info/top_level.txt