Metadata-Version: 1.0
Name: s3vcp
Version: 0.3.1
Summary: A simple s3 file/directory synchronizer, that has the unique abilities to use multiple threads and only copy files with a changed md5 hash.
Home-page: http://bitbucket.org/madssj/s3vcp/
Author: Mads Sulau Joergensen
Author-email: mads@sulau.dk
License: BSD
Keywords: boto s3 version upload sync
Platform: UNKNOWN
